{
  "brackets": {
    "single": [
      { "rate": 0.1, "min": 0, "max": 1160000 },
      { "rate": 0.12, "min": 1160001, "max": 4715000 },
      { "rate": 0.22, "min": 4715001, "max": 10052500 },
      { "rate": 0.24, "min": 10052501, "max": 19195000 },
      { "rate": 0.32, "min": 19195001, "max": 24372500 },
      { "rate": 0.35, "min": 24372501, "max": 60935000 },
      { "rate": 0.37, "min": 60935001, "max": null }
    ],
    "married_joint": [
      { "rate": 0.1, "min": 0, "max": 2320000 },
      { "rate": 0.12, "min": 2320001, "max": 9430000 },
      { "rate": 0.22, "min": 9430001, "max": 20105000 },
      { "rate": 0.24, "min": 20105001, "max": 38390000 },
      { "rate": 0.32, "min": 38390001, "max": 48745000 },
      { "rate": 0.35, "min": 48745001, "max": 73120000 },
      { "rate": 0.37, "min": 73120001, "max": null }
    ],
    "married_separate": [
      { "rate": 0.1, "min": 0, "max": 1160000 },
      { "rate": 0.12, "min": 1160001, "max": 4715000 },
      { "rate": 0.22, "min": 4715001, "max": 10052500 },
      { "rate": 0.24, "min": 10052501, "max": 19195000 },
      { "rate": 0.32, "min": 19195001, "max": 24372500 },
      { "rate": 0.35, "min": 24372501, "max": 36560000 },
      { "rate": 0.37, "min": 36560001, "max": null }
    ],
    "head_of_household": [
      { "rate": 0.1, "min": 0, "max": 1655000 },
      { "rate": 0.12, "min": 1655001, "max": 6310000 },
      { "rate": 0.22, "min": 6310001, "max": 10050000 },
      { "rate": 0.24, "min": 10050001, "max": 19195000 },
      { "rate": 0.32, "min": 19195001, "max": 24370000 },
      { "rate": 0.35, "min": 24370001, "max": 60935000 },
      { "rate": 0.37, "min": 60935001, "max": null }
    ]
  },
  "standardDeduction": {
    "single": 1460000,
    "married_joint": 2920000,
    "married_separate": 1460000,
    "head_of_household": 2190000
  }
}
